<?xml version="1.0" encoding="UTF-8"?>
<templates id="template" xml:space="preserve">

<!--//This displays the 1st form when a product is scanned through mobile  -->
<t t-extend="location_view">
    <t t-jquery="img" t-operation="replace">
        <div class="o_stock_mobile_barcode_container">
            <a class="btn btn-primary o_stock_mobile_barcode"> <i
	class="fa fa-camera fa-2x o_mobile_barcode_camara"></i> <div>Tap to scan</div></a>
            <img src="/stock_barcode/static/img/barcode.png" />
        </div>
    </t>
</t>

<t t-extend="location_menu">
    <t t-jquery="img" t-operation="replace">
        <div class="o_stock_mobile_barcode_container">
            <a class="btn btn-primary o_stock_mobile_barcode"> <i
	class="fa fa-camera fa-2x o_mobile_barcode_camara"></i> <div>Tap to scan</div></a>
            <img src="/stock_barcode/static/img/barcode.png" />
        </div>
    </t>
</t>


</templates>
